MANIFEST.in
setup.py
jm/__init__.py
jm/map.py
jm.egg-info/PKG-INFO
jm.egg-info/SOURCES.txt
jm.egg-info/dependency_links.txt
jm.egg-info/requires.txt
jm.egg-info/top_level.txt
jm/js/init.js
jm/js/map_add_layer.js
jm/js/map_add_source.js
jm/js/map_fit_source.js
jm/js/map_init.js
jm/js/map_remove.js
jm/js/map_set_camera.js
jm/layers/__init__.py
jm/layers/fill.py
jm/layers/line.py
jm/sources/__init__.py
jm/sources/geojson.py