Metadata-Version: 1.0
Name: jm
Version: 0.1.2
Summary: Jupyter Maps
Home-page: https://github.com/iced/jm
Author: Andrew Kirilenko
Author-email: iced@gojuno.com
License: UNKNOWN
Platform: UNKNOWN
